LICENSE
MANIFEST.in
README.md
setup.cfg
setup.py
KeyHarbor.egg-info/PKG-INFO
KeyHarbor.egg-info/SOURCES.txt
KeyHarbor.egg-info/dependency_links.txt
KeyHarbor.egg-info/requires.txt
KeyHarbor.egg-info/top_level.txt
keyharbor/__init__.py
keyharbor/client.py
keyharbor/exceptions.py